legate_wrapper/__init__.py
legate_wrapper/include/legate_mpi_wrapper/legate_mpi_wrapper/mpi_wrapper.h
legate_wrapper/include/legate_mpi_wrapper/legate_mpi_wrapper/mpi_wrapper_types.h
legate_wrapper/include/realm_ucp_bootstrap/realm_ucp_bootstrap/bootstrap.h
legate_wrapper/include/realm_ucp_bootstrap/realm_ucp_bootstrap/bootstrap_util.h
legate_wrapper/lib64/liblegate_mpi_wrapper.so
legate_wrapper/lib64/liblegate_mpi_wrapper.so.1
legate_wrapper/lib64/librealm_ucp_bootstrap_mpi.so
legate_wrapper/lib64/librealm_ucp_bootstrap_mpi.so.1
legate_wrapper/lib64/cmake/legate_mpi_wrapper/mpi_wrapperConfig.cmake
legate_wrapper/lib64/cmake/legate_mpi_wrapper/mpi_wrapperConfigVersion.cmake
legate_wrapper/lib64/cmake/legate_mpi_wrapper/mpi_wrapperTargets.cmake
legate_wrapper/lib64/cmake/realm_ucp_bootstrap/realm_ucp_bootstrapConfig.cmake
legate_wrapper/lib64/cmake/realm_ucp_bootstrap/realm_ucp_bootstrapConfigVersion.cmake
legate_wrapper/lib64/cmake/realm_ucp_bootstrap/realm_ucp_bootstrapTargets.cmake
legate_wrapper_ww_ompi-0.1.3.dist-info/METADATA
legate_wrapper_ww_ompi-0.1.3.dist-info/WHEEL
legate_wrapper_ww_ompi-0.1.3.dist-info/top_level.txt
legate_wrapper_ww_ompi-0.1.3.dist-info/RECORD
